mds3fl/__init__.py
mds3fl/fl_module.py
mds3fl-0.1.0.dist-info/METADATA
mds3fl-0.1.0.dist-info/WHEEL
mds3fl-0.1.0.dist-info/top_level.txt
mds3fl-0.1.0.dist-info/RECORD
